aiomysql/.gitignore
aiomysql/__init__.py
aiomysql/_scm_version.pyi
aiomysql/_version.py
aiomysql/connection.py
aiomysql/cursors.py
aiomysql/log.py
aiomysql/pool.py
aiomysql/utils.py
aiomysql/sa/__init__.py
aiomysql/sa/connection.py
aiomysql/sa/engine.py
aiomysql/sa/exc.py
aiomysql/sa/result.py
aiomysql/sa/transaction.py
hopsworks_aiomysql-0.2.1.dist-info/LICENSE
hopsworks_aiomysql-0.2.1.dist-info/METADATA
hopsworks_aiomysql-0.2.1.dist-info/WHEEL
hopsworks_aiomysql-0.2.1.dist-info/top_level.txt
hopsworks_aiomysql-0.2.1.dist-info/RECORD
