Metadata-Version: 2.1
Name: hopsworks-aiomysql
Version: 0.2.1
Summary: MySQL driver for asyncio.
Home-page: https://github.com/logicalclocks/aiomysql
Download-URL: https://pypi.python.org/pypi/aiomysql
Author: Hopsworks Devs
Author-email: info@hopsworks.ai
License: MIT
Project-URL: CI: GitHub, https://github.com/logicalclocks/aiomysql/actions
Project-URL: Docs: RTD, https://aiomysql.readthedocs.io/
Project-URL: GitHub: repo, https://github.com/logicalclocks/aiomysql
Project-URL: GitHub: issues, https://github.com/logicalclocks/aiomysql/issues
Project-URL: GitHub: discussions, https://github.com/logicalclocks/aiomysql/discussions
Keywords: mysql,mariadb,asyncio,aiomysql
Platform: POSIX
Classifier: License :: OSI Approved :: MIT License
Classifier: Intended Audience :: Developers
Classifier: Programming Language :: Python :: 3
Classifier: Programming Language :: Python :: 3.7
Classifier: Programming Language :: Python :: 3.8
Classifier: Programming Language :: Python :: 3.9
Classifier: Programming Language :: Python :: 3.10
Classifier: Operating System :: POSIX
Classifier: Environment :: Web Environment
Classifier: Development Status :: 3 - Alpha
Classifier: Topic :: Database
Classifier: Topic :: Database :: Front-Ends
Classifier: Framework :: AsyncIO
Requires-Python: >=3.7
License-File: LICENSE
Requires-Dist: PyMySQL>=1.0
Provides-Extra: sa
Requires-Dist: sqlalchemy<=2.0.29,>=1.3; extra == "sa"
Provides-Extra: rsa
Requires-Dist: PyMySQL[rsa]>=1.0; extra == "rsa"
